AUTHORS.rst
CONTRIBUTING.rst
HISTORY.rst
LICENSE
MANIFEST.in
README.rst
setup.cfg
setup.py
docs/Makefile
docs/authors.rst
docs/conf.py
docs/contributing.rst
docs/history.rst
docs/index.rst
docs/installation.rst
docs/make.bat
docs/readme.rst
docs/usage.rst
example/data.json
example/template.j2
lois_lane/__init__.py
lois_lane/cli.py
lois_lane/lois_lane.py
lois_lane/template_helpers.py
lois_lane.egg-info/PKG-INFO
lois_lane.egg-info/SOURCES.txt
lois_lane.egg-info/dependency_links.txt
lois_lane.egg-info/entry_points.txt
lois_lane.egg-info/not-zip-safe
lois_lane.egg-info/requires.txt
lois_lane.egg-info/top_level.txt
tests/__init__.py
tests/test_lois_lane.py