Metadata-Version: 1.1
Name: lois-lane
Version: 0.0.1
Summary: A tool to write reports.
Home-page: https://github.com/ralsina/lois_lane
Author: Roberto Alsina
Author-email: roberto.alsina@gmail.com
License: MIT license
Keywords: lois_lane
Platform: UNKNOWN
Classifier: Development Status :: 2 - Pre-Alpha
Classifier: Intended Audience :: Developers
Classifier: License :: OSI Approved :: MIT License
Classifier: Natural Language :: English
Classifier: Programming Language :: Python :: 2
Classifier: Programming Language :: Python :: 2.6
Classifier: Programming Language :: Python :: 2.7
Classifier: Programming Language :: Python :: 3
Classifier: Programming Language :: Python :: 3.3
Classifier: Programming Language :: Python :: 3.4
Classifier: Programming Language :: Python :: 3.5
